seq/fetch/instrmem.v
module instruction_memory(clk,pc,imem_error,Byte0,Byte19);

input clk;
input[63:0] pc;
output reg imem_error;
output reg[7:0] Byte0;
output reg[71:0] Byte19;

reg [0:7] instr_mem[0:2047];

initial begin
	
//irmovq %16 %r12
instr_mem[0] <= 8'b00110000; //icode ifun
instr_mem[1] <= 8'b11111000; //reg 15 8
instr_mem[2] <= 8'b00010000; // 1 0
instr_mem[3] <= 8'b00000000; // 0 0 
instr_mem[4] <= 8'b00000000;
instr_mem[5] <= 8'b00000000;
instr_mem[6] <= 8'b00000000;
instr_mem[7] <= 8'b00000000;
instr_mem[8] <= 8'b00000000;
instr_mem[9] <= 8'b00000000;

//irmovq %10 %rdi
instr_mem[10] <= 8'b00110000; //icode ifun 3 0
instr_mem[11] <= 8'b11110111; //reg F 7
instr_mem[12] <= 8'b00001010; // 10 : 0 A
instr_mem[13] <= 8'b00000000;
instr_mem[14] <= 8'b00000000;
instr_mem[15] <= 8'b00000000;
instr_mem[16] <= 8'b00000000;
instr_mem[17] <= 8'b00000000;
instr_mem[18] <= 8'b00000000;
instr_mem[19] <= 8'b00000000;

//rmmovq %r12 %(rdi)
instr_mem[20] <= 8'b01000000; //icode ifun 3 0
instr_mem[21] <= 8'b11000111; //reg 
instr_mem[22] <= 8'b00000000; // 10 : 0 A
instr_mem[23] <= 8'b00000000;
instr_mem[24] <= 8'b00000000;
instr_mem[25] <= 8'b00000000;
instr_mem[26] <= 8'b00000000;
instr_mem[27] <= 8'b00000000;
instr_mem[28] <= 8'b00000000;
instr_mem[29] <= 8'b00000000;
//call
instr_mem[30] <= 8'b10000000; //icode ifun: 8 0 
instr_mem[31] <= 8'b10010000; 
instr_mem[32] <= 8'b00000000;
instr_mem[33] <= 8'b00000000;
instr_mem[34] <= 8'b00000000;
instr_mem[35] <= 8'b00000000;
instr_mem[36] <= 8'b00000000;
instr_mem[37] <= 8'b00000000;
instr_mem[38] <= 8'b00000000;

//halt
instr_mem[29] <= 8'b00000000; // 00


// irmovq $8 %r8
instr_mem[112] <= 8'b00110000; //icode ifun
instr_mem[113] <= 8'b11111000; //reg
instr_mem[114] <= 8'b00001000;
instr_mem[115] <= 8'b00000000;
instr_mem[116] <= 8'b00000000;
instr_mem[117] <= 8'b00000000;
instr_mem[118] <= 8'b00000000;
instr_mem[119] <= 8'b00000000;
instr_mem[120] <= 8'b00000000;
instr_mem[121] <= 8'b00000000;

// irmovq %1 %rd
instr_mem[122] <= 8'b00110000; //icode ifun
instr_mem[123] <= 8'b11111001; //reg
instr_mem[124] <= 8'b00000001;
instr_mem[125] <= 8'b00000000;
instr_mem[126] <= 8'b00000000;
instr_mem[127] <= 8'b00000000;
instr_mem[128] <= 8'b00000000;
instr_mem[129] <= 8'b00000000;
instr_mem[130] <= 8'b00000000;
instr_mem[131] <= 8'b00000000;
// xorq %rax % rax  %rax =0
instr_mem[132] <= 8'b01100011; //icode ifun
instr_mem[133] <= 8'b00000000; //reg

// andq %rsi %rsi -- set CC %rsi =6
instr_mem[134] <= 8'b01100010; //icode ifun
instr_mem[135] <= 8'b01100110; //reg
// jmp test- some memory address
instr_mem[136] <= 8'b01110000; //icode ifun
instr_mem[137] <= 8'b01100110; //reg
instr_mem[138] <= 8'b00010000;
instr_mem[139] <= 8'b00000000;
instr_mem[140] <= 8'b00000000;
instr_mem[141] <= 8'b00000000;
instr_mem[142] <= 8'b00000000;
instr_mem[143] <= 8'b00000000;
instr_mem[144] <= 8'b00000000;


// loop:
instr_mem[145] <= 8'b01100001; //icode ifun
instr_mem[146] <= 8'b01100110; //reg

//test:
//jne loop;
instr_mem[147] <= 8'b01110000; //icode ifun
instr_mem[148] <= 8'b11110100; //reg
instr_mem[149] <= 8'b00000000; //
instr_mem[150] <= 8'b00000000; //
instr_mem[151] <= 8'b00000000; //
instr_mem[152] <= 8'b00000000; //
instr_mem[153] <= 8'b00000000; //
instr_mem[154] <= 8'b00000000; //
instr_mem[155] <= 8'b00000000; //

//ret
instr_mem[156] <= 8'b10010000; // 9 0 



end


always @(pc) begin

	if(pc > 64'd2047) begin
		imem_error <= 1'b1;
		Byte0 <= 8'b00000000;

	end
	else begin
		imem_error = 1'b0;
		Byte0 = instr_mem[pc];
		Byte19[7:0] <= instr_mem[pc+1];
		Byte19[15:8] <= instr_mem[pc+2];
		Byte19[23:16] <= instr_mem[pc+3];
		Byte19[31:24] <= instr_mem[pc+4];
		Byte19[39:32] <= instr_mem[pc+5];
		Byte19[47:40] <= instr_mem[pc+6];
		Byte19[55:48] <= instr_mem[pc+7];
		Byte19[63:56] <= instr_mem[pc+8];
		Byte19[71:64] <= instr_mem[pc+9];

		
	end


	
end


endmodule

seq/fetch/fetch.v
// reads instructions from intruction memory 
// finding values of icode, ifun, rA, rB, valC using the instructions


module split(Byte0, icode, ifun);

input [7:0] Byte0;
output [3:0] icode;
output [3:0] ifun;

    assign icode = Byte0[7:4];
    assign ifun = Byte0[3:0];

endmodule


module Need_VALC(icode, need_valC);
input [3:0] icode;
output reg need_valC;

always @(icode)
    begin
    case (icode)
        4'h3, 4'h4, 4'h5, 4'h7, 4'h8:
            begin
                assign need_valC = 1'b1;
            end
        4'h1, 4'h2, 4'h6, 4'h6, 4'h9, 4'hA, 4'hB:
            begin
                assign need_valC = 1'b0;
            end

        default: need_valC = 1'b0;
    endcase
    end
endmodule


module Need_REGIDS(icode, need_regids);

input [3:0] icode;
output reg need_regids;

    always @(icode)
        begin
        case (icode)
            4'h2, 4'h3, 4'h4, 4'h5, 4'h6, 4'hA, 4'hB:
                begin
                    assign need_regids = 1'b1;
                end
            4'h1, 4'h7, 4'h8, 4'h9:
                begin
                    assign need_regids = 1'b0;
                end

            default: need_regids = 1'b0;
        endcase
        end

endmodule


module align(Byte19,need_regids,rA,rB,valC);

input [71:0] Byte19;
input need_regids;
output [3:0] rA;
output [3:0] rB;
output [63:0] valC;

    assign rA = Byte19[7:4] ;
    assign rB = Byte19[3:0];
    assign valC = need_regids ? Byte19[71:8]:Byte19[63:0];

  
endmodule

module PC_INCREMENT(pc, icode, need_regids, need_valC, valP);

input[63:0] pc;
input[3:0] icode;
input need_regids;
input need_valC;

reg halt;
output [63:0] valP;

always @(icode) begin

      if(icode == 4'b000) begin
        halt <= 1'b1;
    end
    else
        halt <= 1'b0;
    
end
  

    assign valP = halt ? pc:(need_valC ? (need_regids ? pc+10:pc+9):(need_regids ? pc+2:pc+1));


endmodule

module INSTR_VALID(icode, instr_valid);
input [3:0] icode;
output reg instr_valid;

always @(icode)
    begin
    case (icode)
        4'h0, 4'h1, 4'h2, 4'h3, 4'h4, 4'h5, 4'h6, 4'h7, 4'h8, 4'h9, 4'hA, 4'hB:
            begin
                assign instr_valid = 1'b1;
            end
    
        default: instr_valid = 1'b0;
    endcase
    end


endmodule

seq/fetch/fetch_tb.v
`timescale 1ns / 1ps

module fetch_tb; 

reg clk; 
reg [63:0] pc; 
wire [7:0] Byte0;
wire [71:0] Byte19;
wire [3:0] icode; 
wire [3:0] ifun;

wire need_regids;
wire need_valC;
wire instr_valid;
wire imem_error;

wire [3:0] rA;
wire [3:0] rB;

wire [63:0] valP;
wire [63:0] valC;

reg [7:0] instr_mem [2047:0];

split sp(.Byte0(Byte0), .icode(icode), .ifun(ifun));
align al(.Byte19(Byte19), .need_regids(need_regids), .rA(rA), .rB(rB), .valC(valC));
PC_INCREMENT PC_i(.pc(pc), .need_regids(need_regids), .need_valC(need_valC), .valP(valP));
INSTR_VALID i_valid(.icode(icode), .instr_valid(instr_valid));
Need_REGIDS nreg(.icode(icode), .need_regids(need_regids));
Need_VALC n_valC(.icode(icode), .need_valC(need_valC));
instruction_memory InstMem(.clk(clk),.pc(pc),.imem_error(imem_error),.Byte0(Byte0),.Byte19(Byte19));


initial begin
    $dumpfile("fetch_test.vcd");
    $dumpvars(0, fetch_tb);

    clk = 0; 
    pc = 64'd1;

    #10 clk = ~clk;
    #10 clk = ~clk; 
    #10 clk = ~clk; pc=64'd0;
    #10 clk = ~clk; 
    #10 clk = ~clk; pc=valP;
    #10 clk = ~clk; 
    #10 clk = ~clk; pc=valP;
    #10 clk = ~clk; 
    #10 clk = ~clk; pc=valP;
    #10 clk = ~clk; 
    #10 clk = ~clk; pc=64'd112;
    #10 clk = ~clk; 
    #10 clk = ~clk; pc=valP;
    #10 clk = ~clk; 
    #10 clk = ~clk; pc=valP;
    #10 clk = ~clk; 
    #10 clk = ~clk; pc=valP;
    #10 clk = ~clk; 
    #10 clk = ~clk; pc=valP;
    #10 clk = ~clk; 
    #10 clk = ~clk; pc=valP;
    #10 clk = ~clk; 
    #10 clk = ~clk; pc=valP;
    #10 clk = ~clk; 
    #10 clk = ~clk; pc=valP;
    #10 clk = ~clk; 
  end  
  
initial begin
		$monitor("clk=%d, pc=%d, icode=%d, ifun=%d, rA=%b, rB=%b, valC=%d, valP=%d, imeme_err = %b\n", clk, pc, icode, ifun, rA, rB, valC, valP,imem_error);

end

endmodule

seq/fetch/fetch_test.vcd
$date
	Tue Mar 08 10:57:56 2022
$end
$version
	Icarus Verilog
$end
$timescale
	1ps
$end
$scope module fetch_tb $end
$var wire 64 ! valP [63:0] $end
$var wire 64 " valC [63:0] $end
$var wire 4 # rB [3:0] $end
$var wire 4 $ rA [3:0] $end
$var wire 1 % need_valC $end
$var wire 1 & need_regids $end
$var wire 1 ' instr_valid $end
$var wire 1 ( imem_error $end
$var wire 4 ) ifun [3:0] $end
$var wire 4 * icode [3:0] $end
$var wire 72 + Byte19 [71:0] $end
$var wire 8 , Byte0 [7:0] $end
$var reg 1 - clk $end
$var reg 64 . pc [63:0] $end
$scope module InstMem $end
$var wire 1 - clk $end
$var wire 64 / pc [63:0] $end
$var reg 8 0 Byte0 [7:0] $end
$var reg 72 1 Byte19 [71:0] $end
$var reg 1 ( imem_error $end
$upscope $end
$scope module PC_i $end
$var wire 4 2 icode [3:0] $end
$var wire 64 3 pc [63:0] $end
$var wire 64 4 valP [63:0] $end
$var wire 1 % need_valC $end
$var wire 1 & need_regids $end
$var reg 1 5 halt $end
$upscope $end
$scope module al $end
$var wire 72 6 Byte19 [71:0] $end
$var wire 64 7 valC [63:0] $end
$var wire 4 8 rB [3:0] $end
$var wire 4 9 rA [3:0] $end
$var wire 1 & need_regids $end
$upscope $end
$scope module i_valid $end
$var wire 4 : icode [3:0] $end
$var reg 1 ' instr_valid $end
$upscope $end
$scope module n_valC $end
$var wire 4 ; icode [3:0] $end
$var reg 1 % need_valC $end
$upscope $end
$scope module nreg $end
$var wire 4 < icode [3:0] $end
$var reg 1 & need_regids $end
$upscope $end
$scope module sp $end
$var wire 8 = Byte0 [7:0] $end
$var wire 4 > ifun [3:0] $end
$var wire 4 ? icode [3:0] $end
$upscope $end
$upscope $end
$enddefinitions $end
#0
$dumpvars
bx ?
bx >
bx =
bx <
bx ;
bx :
bx 9
bx 8
bx 7
bx 6
05
b0x01x 4
b1 3
bz 2
bx 1
bx 0
b1 /
b1 .
0-
bx ,
bx +
bx *
bx )
0(
x'
x&
x%
bx $
bx #
bx "
b0x01x !
$end
#10000
1-
#20000
0-
#30000
b10000 "
b10000 7
b1111 $
b1111 9
b1000 #
b1000 8
b1000011111000 +
b1000011111000 1
b1000011111000 6
1%
1&
1'
b1010 !
b1010 4
b11 *
b11 :
b11 ;
b11 <
b11 ?
b0 )
b0 >
b110000 ,
b110000 0
b110000 =
b0 .
b0 /
b0 3
1-
#40000
0-
#50000
b1010 "
b1010 7
b111 #
b111 8
b101011110111 +
b101011110111 1
b101011110111 6
b10100 !
b10100 4
b1010 .
b1010 /
b1010 3
1-
#60000
0-
#70000
b0 "
b0 7
b1100 $
b1100 9
b11000111 +
b11000111 1
b11000111 6
b11110 !
b11110 4
b100 *
b100 :
b100 ;
b100 <
b100 ?
b1000000 ,
b1000000 0
b1000000 =
b10100 .
b10100 /
b10100 3
1-
#80000
0-
#90000
b1001 $
b1001 9
b0 #
b0 8
bx0000000000000000000000000000000000000000000000000000000010010000 +
bx0000000000000000000000000000000000000000000000000000000010010000 1
bx0000000000000000000000000000000000000000000000000000000010010000 6
b10010000 "
b10010000 7
0&
b100111 !
b100111 4
b1000 *
b1000 :
b1000 ;
b1000 <
b1000 ?
b10000000 ,
b10000000 0
b10000000 =
b11110 .
b11110 /
b11110 3
1-
#100000
0-
#110000
b1111 $
b1111 9
b1000 #
b1000 8
b100011111000 +
b100011111000 1
b100011111000 6
b1000 "
b1000 7
1&
b1111010 !
b1111010 4
b11 *
b11 :
b11 ;
b11 <
b11 ?
b110000 ,
b110000 0
b110000 =
b1110000 .
b1110000 /
b1110000 3
1-
#120000
0-
#130000
b1 "
b1 7
b1001 #
b1001 8
b111111001 +
b111111001 1
b111111001 6
b10000100 !
b10000100 4
b1111010 .
b1111010 /
b1111010 3
1-
#140000
0-
#150000
b1000001100110011100000110011001100010 "
b1000001100110011100000110011001100010 7
b0 $
b0 9
b0 #
b0 8
b100000110011001110000011001100110001000000000 +
b100000110011001110000011001100110001000000000 1
b100000110011001110000011001100110001000000000 6
0%
b10000110 !
b10000110 4
b110 *
b110 :
b110 ;
b110 <
b110 ?
b11 )
b11 >
b1100011 ,
b1100011 0
b1100011 =
b10000100 .
b10000100 /
b10000100 3
1-
#160000
0-
#170000
b100000110011001110000 "
b100000110011001110000 7
b110 $
b110 9
b110 #
b110 8
b10000011001100111000001100110 +
b10000011001100111000001100110 1
b10000011001100111000001100110 6
b10001000 !
b10001000 4
b10 )
b10 >
b1100010 ,
b1100010 0
b1100010 =
b10000110 .
b10000110 /
b10000110 3
1-
#180000
0-
#190000
b11000010000000000000000000000000000000000000000000000000001000001100110 +
b11000010000000000000000000000000000000000000000000000000001000001100110 1
b11000010000000000000000000000000000000000000000000000000001000001100110 6
b1000001100110 "
b1000001100110 7
0&
1%
b10010001 !
b10010001 4
b111 *
b111 :
b111 ;
b111 <
b111 ?
b0 )
b0 >
b1110000 ,
b1110000 0
b1110000 =
b10001000 .
b10001000 /
b10001000 3
1-
#200000
0-
#210000
b111101000111000001100110 +
b111101000111000001100110 1
b111101000111000001100110 6
b1111010001110000 "
b1111010001110000 7
0%
1&
b10010011 !
b10010011 4
b110 *
b110 :
b110 ;
b110 <
b110 ?
b1 )
b1 >
b1100001 ,
b1100001 0
b1100001 =
b10010001 .
b10010001 /
b10010001 3
1-
#220000
0-
#230000
b1111 $
b1111 9
b100 #
b100 8
b100100000000000000000000000000000000000000000000000000000000000011110100 +
b100100000000000000000000000000000000000000000000000000000000000011110100 1
b100100000000000000000000000000000000000000000000000000000000000011110100 6
b11110100 "
b11110100 7
0&
1%
b10011100 !
b10011100 4
b111 *
b111 :
b111 ;
b111 <
b111 ?
b0 )
b0 >
b1110000 ,
b1110000 0
b1110000 =
b10010011 .
b10010011 /
b10010011 3
1-
#240000
0-
#250000
bx "
bx 7
bx $
bx 9
bx #
bx 8
bx +
bx 1
bx 6
0%
b10011101 !
b10011101 4
b1001 *
b1001 :
b1001 ;
b1001 <
b1001 ?
b10010000 ,
b10010000 0
b10010000 =
b10011100 .
b10011100 /
b10011100 3
1-
